CHIP_aREST/__init__.py
CHIP_aREST/aREST.py
CHIP_aREST-0.3.data/scripts/chip-arest-basic.py
CHIP_aREST-0.3.data/scripts/chip-arest-cloud.py
CHIP_aREST-0.3.dist-info/metadata.json
CHIP_aREST-0.3.dist-info/LICENSE.txt
CHIP_aREST-0.3.dist-info/top_level.txt
CHIP_aREST-0.3.dist-info/WHEEL
CHIP_aREST-0.3.dist-info/METADATA
CHIP_aREST-0.3.dist-info/DESCRIPTION.rst
CHIP_aREST-0.3.dist-info/RECORD
