Metadata-Version: 2.0
Name: CHIP-aREST
Version: 0.3
Summary: A module to control the CHIP IO channels via a REST API
Home-page: https://github.com/xtacocorex/CHIP_aREST/
Author: Robert Wolterman
Author-email: robert.wolterman@gmail.com
License: MIT
Keywords: CHIP CHIPPRO NextThingCo IO GPIO PWM ADC SERVO REST
Platform: UNKNOWN
Classifier: Development Status :: 3 - Alpha
Classifier: Operating System :: POSIX :: Linux
Classifier: License :: OSI Approved :: MIT License
Classifier: Intended Audience :: Developers
Classifier: Programming Language :: Python :: 2.7
Classifier: Programming Language :: Python :: 3
Classifier: Topic :: Software Development
Classifier: Topic :: Home Automation
Classifier: Topic :: System :: Hardware
Requires-Dist: flask
Requires-Dist: CHIP-IO
Requires-Dist: requests
Requires-Dist: paho-mqtt
